README.md
setup.py
shufflemilky/__init__.py
shufflemilky/shufflemilky.py
shufflemilky.egg-info/PKG-INFO
shufflemilky.egg-info/SOURCES.txt
shufflemilky.egg-info/dependency_links.txt
shufflemilky.egg-info/entry_points.txt
shufflemilky.egg-info/requires.txt
shufflemilky.egg-info/top_level.txt