Metadata-Version: 1.0
Name: shufflemilky
Version: 0.4.0
Summary: A simple shuffle player written in Python.
Home-page: http://pypi.python.org/pypi/shufflemilky/
Author: Samuel Freitas
Author-email: samuelfreitas@linuxmail.org
License: MIT
Platform: unix
